ml_list/__init__.py
ml_list/text_reader.py
ml_list/data/my_code.py
ml_list-0.1.dist-info/METADATA
ml_list-0.1.dist-info/WHEEL
ml_list-0.1.dist-info/top_level.txt
ml_list-0.1.dist-info/RECORD
