Metadata-Version: 2.1
Name: ml-list
Version: 0.1
Summary: List of all Libraries
Home-page: https://github.com/savioratharv/prac_testing
Author: davinci003
Author-email: freegpt00@gmail.com
